datetimeparse.cpython-38-x86_64-linux-gnu.so
datetimeparse-0.5.6.dist-info/top_level.txt
datetimeparse-0.5.6.dist-info/LICENSE.txt
datetimeparse-0.5.6.dist-info/RECORD
datetimeparse-0.5.6.dist-info/WHEEL
datetimeparse-0.5.6.dist-info/METADATA
