Metadata-Version: 2.1
Name: datetimeparse
Version: 0.5.6
Summary: A fast utility to parse and output timestamps in ISO8601/RFC3339 format, written mostly in C.
Home-page: https://gitlab.com/krcrouse/datetimeparse
Author: Kevin Crouse
Author-email: krcrouse@gmail.com
License: UNKNOWN
Platform: UNKNOWN
Classifier: Programming Language :: Python :: 3.7
Classifier: License :: OSI Approved :: Apache Software License
Classifier: Operating System :: OS Independent
Classifier: Development Status :: 4 - Beta
